[{"key": ["TWENTYFOUR", "FIFTHYFIVE", "THIRTYONE", "FIFTHYFOUR"], "policy": "((((\"FOURTYEIGHT\" AND \"TWENTYSEVEN\") AND ((\"FIVE\" OR \"EIGHTEEN\") OR (\"ONE\" OR \"NINE\"))) AND (\"SIXTY\" OR ((\"FIFTYTHREEE\" OR \"SIXTEEN\") OR \"FOURTYFIVE\"))) OR ((((((\"FIFTEEN\" OR \"TWENTYFOUR\") AND \"FIFTHYFIVE\") OR \"TWENTYEIGHT\") AND \"THIRTYONE\") OR ((\"THIRTY\" OR \"THIRTEEN\") AND ((\"EIGHT\" OR (\"FIFTHYFOUR\" OR \"TWENTYTHREE\")) AND (\"FOURTYFOUR\" OR (\"FOURTYSIX\" AND \"FOURTEEN\"))))) OR (((\"FOUR\" AND (\"ELEVEN\" AND \"THREE\")) OR (\"FOURTYTHREE\" AND \"FIFTHYSIX\")) OR ((\"FOURTYTWO\" AND (\"TWENTYSIX\" OR \"THIRTYFOUR\")) OR \"TWO\"))))"}, {"key": ["THIRTYNINE", "ELEVEN", "THIRTY", "FOURTYEIGHT"], "policy": "(((((\"TWENTYONE\" OR \"FIFTYONE\") AND ((\"FIFTHYNINE\" OR \"FIFTHYFOUR\") OR (\"THIRTEEN\" AND \"ONE\"))) AND (\"SIXTY\" AND \"SIXTYFOUR\")) OR ((\"THIRTYONE\" AND ((\"THIRTY\" AND \"TWO\") AND (\"FOURTYTWO\" OR \"FIFTHYSEVEN\"))) AND ((((\"SIXTYONE\" AND \"TWENTYSIX\") AND \"FIVE\") OR \"THIRTYEIGHT\") AND (\"FOURTYFIVE\" AND (\"FOURTYEIGHT\" OR \"FIFTHYFIVE\"))))) OR (((\"TWENTYEIGHT\" OR (\"FOUR\" OR \"FOURTYFOUR\")) OR (\"FOURTY\" OR \"NINE\")) OR (((\"SIXTYTWO\" AND (\"SIX\" AND \"FIFTYTWO\")) OR (\"THIRTYSEVEN\" OR (\"THIRTYTHREE\" OR \"FOURTYSEVEN\"))) OR \"THIRTYNINE\")))"}, {"key": ["TWENTYEIGHT", "TWENTYONE", "TWENTY", "FOURTYNINE"], "policy": "(((\"TWENTYEIGHT\" OR (\"EIGHTEEN\" OR \"SIXTY\")) OR (((\"TEN\" OR \"EIGHT\") OR (((\"FIFTEEN\" OR \"TWENTYTHREE\") AND (\"TWENTYNINE\" AND \"FIVE\")) AND \"TWENTY\")) AND (((\"FOURTYSIX\" OR \"FIFTYTHREEE\") AND \"FOURTYTWO\") AND ((\"FIFTHYSIX\" OR (\"THIRTYFOUR\" OR \"NINE\")) OR ((\"FOURTY\" OR \"THIRTYONE\") OR \"THIRTY\"))))) AND ((((\"FOURTEEN\" OR \"THIRTYSIX\") AND (\"FIFTHYFOUR\" OR \"TWO\")) AND ((\"TWENTYSEVEN\" AND (\"SIXTEEN\" AND \"NINETEEN\")) AND (\"TWENTYFOUR\" AND \"THIRTYNINE\"))) OR ((\"SIXTYTWO\" OR \"TWENTYONE\") OR (\"FOUR\" OR \"FIFTHYNINE\"))))"}, {"key": ["SIX", "FIFTY", "FIFTHYFOUR", "FOURTY"], "policy": "(((\"FOURTYSIX\" OR ((\"FIVE\" AND \"FOURTY\") AND \"TWENTYONE\")) OR ((((\"FOURTYTHREE\" OR \"TWENTYEIGHT\") AND (\"THIRTYSEVEN\" OR \"FIFTYONE\")) OR ((\"ONE\" OR (\"FIFTHYNINE\" OR \"EIGHTEEN\")) OR (\"SIXTY\" AND \"FOURTYEIGHT\"))) OR (\"FIFTEEN\" OR \"THIRTYNINE\"))) OR ((((\"FOURTYSEVEN\" OR \"SIXTYONE\") AND ((\"THIRTYSIX\" AND \"NINETEEN\") AND \"TWENTY\")) AND ((\"TWENTYFIVE\" AND \"FIFTHYSIX\") OR \"ELEVEN\")) OR ((\"SIX\" AND ((\"SEVENTEEN\" OR \"FIFTY\") AND \"FIFTHYFOUR\")) OR ((\"FOURTYNINE\" OR \"TEN\") AND (\"THREE\" OR (\"THIRTYFIVE\" OR \"SEVEN\"))))))"}, {"key": ["FIFTHYFOUR", "THIRTEEN", "SIXTYTWO", "SEVEN"], "policy": "((((\"THIRTYONE\" AND \"FIFTHYSIX\") OR \"TWENTYSIX\") OR ((((\"TWENTYNINE\" OR \"ONE\") AND (\"FIFTHYNINE\" OR \"TWENTYFOUR\")) AND (\"FIFTHYEIGHT\" AND \"THIRTYNINE\")) OR (((\"FIFTEEN\" OR \"NINE\") AND (\"SEVEN\" OR \"TWELVE\")) AND \"FOUR\"))) OR (((((\"EIGHT\" OR \"FIFTYTWO\") OR \"THIRTYTWO\") OR \"FOURTYFIVE\") AND (\"FIFTYONE\" OR (\"FIFTHYSEVEN\" AND (\"TEN\" OR \"SIXTYTWO\")))) OR (((\"FIFTHYFOUR\" AND \"THIRTEEN\") OR ((\"TWENTYSEVEN\" OR \"FOURTYSEVEN\") AND ((\"THIRTYSEVEN\" AND \"TWENTYEIGHT\") OR \"TWENTY\"))) OR ((\"FOURTYFOUR\" AND \"SIXTY\") OR \"FOURTYONE\"))))"}, {"key": ["EIGHTEEN", "FIFTYTWO", "TWO", "FOURTYTHREE"], "policy": "((((\"TWENTYTHREE\" AND \"FIFTEEN\") AND ((((\"TWENTY\" OR \"FOURTYEIGHT\") OR \"TWENTYONE\") AND \"TWELVE\") AND ((\"THIRTYFOUR\" AND \"FIFTHYNINE\") AND \"ELEVEN\"))) AND (((\"SEVEN\" OR \"SIXTEEN\") AND (\"TWENTYFOUR\" AND \"THIRTY\")) AND ((\"EIGHT\" AND \"SEVENTEEN\") AND ((\"ONE\" AND \"THIRTYEIGHT\") AND \"FIFTHYFIVE\")))) OR ((((\"TWENTYNINE\" AND \"THIRTYTWO\") OR \"FIFTHYEIGHT\") OR ((\"EIGHTEEN\" AND \"FIFTYTWO\") AND (\"TWO\" AND \"FOURTYTHREE\"))) OR ((\"FOURTYONE\" OR (\"FOURTYSIX\" OR \"THIRTYSEVEN\")) AND (((\"TEN\" OR \"FOURTEEN\") AND \"TWENTYEIGHT\") OR \"SIXTY\"))))"}, {"key": ["FOURTYFIVE", "SIXTYTWO", "FOURTYTWO", "SIX"], "policy": "((((((\"SEVENTEEN\" OR \"FOURTYFIVE\") AND \"SIXTYTWO\") OR \"SIXTYFOUR\") OR ((\"THIRTY\" AND \"TEN\") OR (\"FOURTYSIX\" OR (\"THREE\" AND \"SEVEN\")))) OR (((\"TWENTYEIGHT\" OR (\"FIFTEEN\" OR \"FOURTYONE\")) OR (\"TWO\" OR \"FIFTHYEIGHT\")) OR (\"THIRTYSEVEN\" AND (\"SIXTYONE\" OR \"FOURTYEIGHT\")))) OR (((\"FIVE\" OR (\"FOURTYSEVEN\" OR \"TWENTYNINE\")) OR ((\"THIRTYFIVE\" AND \"TWENTYFOUR\") AND (\"TWENTYFIVE\" AND \"FIFTHYNINE\"))) AND ((\"THIRTYONE\" OR ((\"TWENTYSIX\" OR \"FIFTYTHREEE\") OR \"THIRTYSIX\")) AND ((\"TWENTY\" AND \"FIFTY\") OR (\"FIFTHYFIVE\" OR \"FIFTHYFOUR\")))))"}, {"key": ["TWENTYEIGHT", "SIXTYTHREE", "ONE", "THIRTYFIVE"], "policy": "((((((\"FIVE\" AND \"FIFTHYEIGHT\") AND \"FOURTYSEVEN\") AND ((\"FOURTYTWO\" OR (\"NINETEEN\" AND \"TWO\")) OR (\"SEVENTEEN\" AND \"THIRTYSEVEN\"))) AND (\"THREE\" OR (\"SIX\" OR (\"FIFTEEN\" AND \"SIXTY\")))) OR ((\"THIRTYSIX\" OR (\"TWENTYEIGHT\" OR \"TWENTYSIX\")) AND (((\"FIFTHYFIVE\" OR \"FOURTYTHREE\") AND (\"FOURTYONE\" OR \"FIFTHYFOUR\")) OR (\"SIXTYTHREE\" AND (\"ONE\" OR \"EIGHTEEN\"))))) OR ((((\"FOURTEEN\" AND \"THIRTYNINE\") AND (\"THIRTYFOUR\" OR \"TWENTYTWO\")) OR (\"EIGHT\" AND \"THIRTYFIVE\")) AND (\"SEVEN\" OR (\"FIFTHYSEVEN\" OR (\"FOURTYSIX\" OR \"NINE\")))))"}, {"key": ["TWENTYSEVEN", "FOURTYFOUR", "FIFTYTWO", "FOURTY"], "policy": "(((((\"THREE\" AND \"SIXTEEN\") AND (\"THIRTYSIX\" AND \"FOURTYTWO\")) AND ((\"FIFTY\" AND \"FIVE\") OR \"SIXTYTWO\")) OR (((\"TWENTYSEVEN\" AND \"FOURTYFOUR\") AND (((\"THIRTYTWO\" AND \"SEVEN\") AND \"NINE\") OR (\"FIFTYTWO\" OR \"FIFTHYFOUR\"))) AND (\"FOURTY\" OR \"FIFTHYFIVE\"))) OR ((((\"FIFTHYNINE\" OR \"TWENTY\") OR (\"FOURTYEIGHT\" AND \"THIRTYSEVEN\")) OR ((\"TWELVE\" OR \"TWENTYTWO\") OR (\"FIFTHYEIGHT\" OR \"THIRTYFOUR\"))) AND (((\"SIX\" OR \"TWENTYTHREE\") OR \"FIFTYTHREEE\") OR ((\"FIFTEEN\" OR \"TEN\") AND (\"TWENTYEIGHT\" AND (\"FOUR\" AND \"TWENTYFIVE\"))))))"}, {"key": ["TWENTYFIVE", "TWENTYONE", "TWENTY", "NINETEEN"], "policy": "(((((\"THIRTY\" OR \"TWENTYNINE\") OR \"FIFTYTHREEE\") OR ((\"FOUR\" AND \"FOURTYTHREE\") AND (\"TWENTYTWO\" AND \"SEVEN\"))) OR ((\"TWENTYFIVE\" AND \"TWENTYONE\") AND ((\"EIGHTEEN\" AND \"SIXTYTHREE\") OR (\"TWENTY\" AND \"NINETEEN\")))) OR ((((\"THIRTYONE\" OR (\"ELEVEN\" AND \"THIRTYNINE\")) OR \"FIFTHYSEVEN\") OR ((\"FOURTYSIX\" OR (\"FOURTYONE\" OR \"THIRTYEIGHT\")) AND (\"THIRTEEN\" AND \"THIRTYTHREE\"))) OR (((\"THIRTYFIVE\" AND (\"THIRTYSIX\" OR (\"TEN\" AND \"FIFTHYFOUR\"))) AND (\"FOURTYEIGHT\" OR (\"THIRTYFOUR\" AND \"FIFTYONE\"))) OR (\"TWENTYFOUR\" AND (\"TWENTYTHREE\" OR \"FOURTYTWO\")))))"}, {"key": ["THIRTYTWO", "SIXTY", "THIRTYTHREE", "TWO"], "policy": "(((((\"THIRTYNINE\" OR (\"EIGHT\" OR \"THIRTY\")) AND ((\"FIFTHYNINE\" AND \"THIRTYONE\") AND \"TWENTYTHREE\")) OR (\"FIVE\" OR (\"FOURTEEN\" OR \"THIRTYTWO\"))) AND ((\"FOURTYTWO\" OR \"SIXTY\") OR ((\"TWELVE\" AND \"TWENTY\") AND (\"SIXTYONE\" AND \"FIFTHYSEVEN\")))) AND (((\"SEVENTEEN\" AND \"SEVEN\") AND ((\"TWENTYSIX\" OR \"FOURTYSEVEN\") AND ((\"SIXTYTHREE\" AND \"NINE\") AND \"TWENTYSEVEN\"))) OR ((((\"FOURTYFIVE\" OR \"TWENTYFOUR\") OR \"TWENTYTWO\") AND (\"THIRTYEIGHT\" AND \"FIFTHYEIGHT\")) OR ((\"THIRTYTHREE\" AND (\"TWO\" OR \"SIXTYTWO\")) OR (\"FOURTYNINE\" AND \"FIFTEEN\")))))"}, {"key": ["THIRTYEIGHT", "FOURTYTWO", "FIFTYONE", "THIRTYONE"], "policy": "(((((\"TEN\" OR (\"FIFTYONE\" OR \"FOURTYEIGHT\")) OR (\"FOURTYFOUR\" AND \"FOURTYONE\")) AND (((\"THIRTYFIVE\" AND \"SIXTYTHREE\") OR ((\"THIRTYONE\" AND \"FIVE\") AND (\"FIFTHYSEVEN\" OR \"THIRTY\"))) OR \"ONE\")) OR (((\"TWENTYFIVE\" AND (\"TWENTYNINE\" AND \"TWENTYSEVEN\")) OR ((\"TWENTY\" OR \"FOURTY\") OR \"FOURTYSEVEN\")) OR ((\"SIXTYONE\" OR \"THIRTYTWO\") AND \"THIRTYNINE\"))) OR ((((\"FIFTEEN\" AND \"SIXTYTWO\") OR \"FOURTEEN\") OR (\"FOURTYSIX\" AND \"FIFTYTHREEE\")) OR ((\"THIRTYFOUR\" OR ((\"FOURTYNINE\" AND \"FIFTHYFIVE\") AND \"THIRTYSIX\")) OR (\"THIRTYEIGHT\" AND \"FOURTYTWO\"))))"}, {"key": ["TWO", "SEVEN", "FIFTHYSEVEN", "TWENTYSIX"], "policy": "((((((\"TWENTYONE\" AND \"TWENTYNINE\") AND \"THIRTYFOUR\") OR \"FIFTYONE\") OR ((\"ONE\" AND (\"FIVE\" OR \"THIRTYFIVE\")) AND \"FOUR\")) OR ((((\"FIFTHYNINE\" OR \"FOURTYEIGHT\") OR \"TWENTYEIGHT\") OR (\"FIFTHYEIGHT\" OR \"FOURTYFIVE\")) OR ((((\"TWENTYFIVE\" AND \"FOURTYSEVEN\") AND \"FOURTEEN\") AND \"THREE\") OR (\"TWO\" OR \"THIRTYTWO\")))) OR (((\"TWENTY\" OR ((\"FIFTHYSEVEN\" OR \"FOURTYTWO\") OR \"FIFTYTWO\")) AND (\"TWENTYTWO\" AND (\"FOURTYSIX\" OR \"SEVENTEEN\"))) AND ((\"THIRTYNINE\" OR (\"TWENTYTHREE\" AND (\"SIXTEEN\" AND \"FOURTYTHREE\"))) OR (\"THIRTYSIX\" AND \"FOURTY\"))))"}, {"key": ["THIRTYTHREE", "THIRTYTWO", "TWENTYFIVE", "THIRTYFOUR"], "policy": "((((\"THIRTYFIVE\" OR (\"TWENTYONE\" AND (\"FIFTHYSIX\" AND \"EIGHTEEN\"))) OR (\"TWENTYSIX\" AND \"FIFTYONE\")) AND ((\"TEN\" AND (\"THIRTYONE\" AND \"FOURTYEIGHT\")) OR (\"THREE\" OR (\"THIRTYSEVEN\" OR (\"THIRTEEN\" AND \"SIXTYTHREE\"))))) OR (((\"THIRTYTHREE\" AND (\"SIXTEEN\" OR \"THIRTYTWO\")) OR (\"FOURTYFOUR\" AND (\"FOURTYFIVE\" AND \"THIRTYSIX\"))) AND (((\"FIFTY\" OR (\"TWENTYFOUR\" OR \"TWENTYFIVE\")) OR (\"TWENTY\" AND \"THIRTYFOUR\")) OR (((\"TWELVE\" OR \"THIRTY\") OR (\"FIFTEEN\" AND \"FIFTYTHREEE\")) AND ((\"THIRTYNINE\" OR \"SIXTYFOUR\") OR (\"SIXTYTWO\" AND \"TWENTYEIGHT\"))))))"}, {"key": ["SIXTYTHREE", "FIFTYTHREEE", "NINETEEN", "FIVE"], "policy": "((((\"SIXTYTHREE\" OR \"TWENTYEIGHT\") OR ((\"THIRTYNINE\" OR \"FOURTYFIVE\") AND \"FOURTYTHREE\")) OR ((((\"TWO\" OR \"FOURTEEN\") OR \"FOURTYTWO\") OR ((\"FIFTYONE\" OR \"FOURTYEIGHT\") AND \"FIFTY\")) OR ((\"FOURTY\" OR \"FOURTYFOUR\") OR ((\"FIFTYTWO\" AND \"THIRTYSEVEN\") AND (\"ELEVEN\" AND \"FIFTHYEIGHT\"))))) AND ((((\"ONE\" OR \"FIFTYTHREEE\") OR (\"TWENTYONE\" OR \"FIFTHYFOUR\")) AND (\"FOURTYSEVEN\" OR ((\"FIFTHYSIX\" OR \"NINETEEN\") AND (\"FIVE\" OR \"SIXTYTWO\")))) OR ((\"THIRTYFIVE\" AND (\"THIRTYTHREE\" OR \"FOURTYSIX\")) AND ((\"THIRTY\" OR \"THIRTYONE\") OR \"THIRTYEIGHT\"))))"}, {"key": ["SIXTYTHREE", "TWO", "FIVE", "FIFTEEN"], "policy": "(((((\"FOURTYTHREE\" AND \"SIXTYFOUR\") OR (\"THIRTYSEVEN\" AND \"THREE\")) OR (\"SIXTYTHREE\" AND ((\"FOURTYNINE\" OR \"TWO\") AND (\"FIVE\" AND \"FIFTEEN\")))) OR ((((\"THIRTYNINE\" OR \"TWENTYTWO\") OR (\"THIRTYONE\" AND \"SIXTEEN\")) AND (\"FOURTEEN\" AND (\"THIRTYTHREE\" AND \"NINETEEN\"))) AND (\"NINE\" AND ((\"SEVENTEEN\" OR \"THIRTYEIGHT\") AND \"FOURTYSIX\")))) OR ((\"TWENTYEIGHT\" OR ((\"SIXTYTWO\" OR \"TEN\") OR \"FIFTHYFOUR\")) AND ((\"FIFTHYSEVEN\" OR (\"TWENTYSEVEN\" AND (\"TWENTYONE\" OR \"FOURTYFOUR\"))) OR ((\"ONE\" AND \"FOURTYONE\") AND (\"EIGHT\" OR \"TWENTY\")))))"}, {"key": ["ONE", "TWENTYFOUR", "TWENTYTWO", "THIRTYNINE"], "policy": "((((\"FIFTHYSIX\" OR (\"TWENTYTHREE\" OR \"SIXTYFOUR\")) OR (\"FIFTHYNINE\" OR \"SIX\")) OR (((\"SIXTYONE\" OR \"FOURTYNINE\") AND (\"THIRTYNINE\" AND \"FIFTYONE\")) OR ((\"ONE\" OR \"SIXTYTHREE\") AND (\"TWENTYFOUR\" AND (\"TWENTYTWO\" OR \"EIGHT\"))))) OR ((((\"FIFTYTHREEE\" AND (\"THIRTYEIGHT\" AND \"FIFTHYEIGHT\")) AND ((\"FOURTYEIGHT\" OR \"FIVE\") OR (\"SIXTY\" OR \"THIRTYFOUR\"))) OR ((\"TWENTYSIX\" OR \"THIRTEEN\") AND ((\"FOURTYTHREE\" OR \"TWENTYEIGHT\") OR (\"FOURTYFOUR\" OR \"FOURTYSIX\")))) AND ((\"NINE\" OR (\"EIGHTEEN\" AND \"THIRTYTHREE\")) AND (\"ELEVEN\" OR \"THREE\"))))"}, {"key": ["SEVENTEEN", "NINETEEN", "FOURTYONE", "FOURTYFOUR"], "policy": "((((((\"TWENTYEIGHT\" OR \"TWENTYNINE\") AND \"TWENTYSEVEN\") OR (\"FIFTHYFOUR\" AND (\"NINE\" OR \"TEN\"))) OR \"FOURTYTHREE\") OR ((((\"SEVENTEEN\" AND \"NINETEEN\") OR \"SIXTYTHREE\") OR \"THREE\") AND ((\"TWELVE\" AND \"FOURTYEIGHT\") OR \"FOURTYONE\"))) OR ((((\"TWENTYTHREE\" OR ((\"FOURTEEN\" OR \"THIRTY\") OR (\"THIRTYFIVE\" OR \"SEVEN\"))) AND \"FIFTYTHREEE\") AND ((\"FOURTYFIVE\" AND \"THIRTYSEVEN\") OR ((\"THIRTYTHREE\" OR \"FIFTHYSIX\") OR \"TWENTYONE\"))) OR (((\"THIRTYONE\" AND \"FOURTYSEVEN\") OR (\"FIVE\" OR \"TWENTYTWO\")) OR ((\"FOURTYSIX\" OR \"SIXTYFOUR\") AND \"THIRTYNINE\"))))"}, {"key": ["TWENTYSEVEN", "THIRTYONE", "TEN", "FIFTY"], "policy": "((((\"TWENTYSEVEN\" OR (\"FOURTYONE\" OR \"SIXTYFOUR\")) AND ((((\"FOURTYFIVE\" OR \"FOURTYTHREE\") AND \"FIFTHYEIGHT\") AND \"THIRTYFOUR\") OR (\"THIRTYONE\" AND \"TEN\"))) AND ((((\"SIX\" OR \"FOUR\") AND (\"FIFTHYNINE\" AND \"THIRTYTWO\")) AND \"FIFTYONE\") OR ((\"TWO\" OR \"TWELVE\") OR \"FIFTY\"))) OR ((((\"EIGHTEEN\" OR \"FIFTYTHREEE\") OR \"TWENTYEIGHT\") AND ((\"FIFTYTWO\" OR \"FIFTHYFIVE\") AND (\"TWENTYFOUR\" AND \"TWENTYNINE\"))) AND (((\"TWENTY\" OR (\"TWENTYSIX\" AND \"FOURTYSIX\")) OR \"FIVE\") OR (\"FOURTYEIGHT\" OR (\"SEVENTEEN\" OR (\"SIXTYTWO\" AND \"FIFTEEN\"))))))"}, {"key": ["FIFTHYSEVEN", "ONE", "FOURTYEIGHT", "TWENTYTWO"], "policy": "(((((\"TWENTYFIVE\" AND (\"FIFTY\" OR \"THIRTYTHREE\")) OR \"FOURTYTHREE\") AND ((\"THIRTY\" OR \"SIXTYTWO\") OR (\"TWENTYSIX\" AND (\"TWELVE\" OR \"FIFTHYNINE\")))) AND ((((\"TWENTYFOUR\" OR \"FOURTYNINE\") AND \"FIFTHYFOUR\") AND ((\"SIXTYTHREE\" AND \"THREE\") OR \"THIRTYEIGHT\")) OR ((\"SIXTY\" OR (\"THIRTYTWO\" AND \"TWENTYTHREE\")) OR (\"FOUR\" AND (\"SIXTYFOUR\" OR \"ELEVEN\"))))) OR (((\"FIFTHYSEVEN\" AND \"ONE\") AND (\"FOURTYEIGHT\" AND \"TWENTYTWO\")) OR (\"FIVE\" OR ((\"FIFTHYEIGHT\" OR \"FIFTHYFIVE\") AND ((\"SEVEN\" AND \"EIGHTEEN\") OR (\"SIXTEEN\" OR \"SIX\"))))))"}]