[{"key": ["THIRTYTHREE", "FOURTEEN", "FOURTY", "TWENTYTHREE", "FOURTYNINE", "FOURTYFOUR", "THIRTYFIVE", "THIRTYONE", "FIFTYTWO", "EIGHT", "NINETEEN", "FIFTYTHREEE", "SIXTEEN", "FIFTHYSIX", "TEN", "TWENTYONE", "TWELVE", "FOURTYFIVE", "FIFTHYNINE", "SIXTY", "TWENTYTWO", "ONE", "TWO", "SEVEN", "THIRTYNINE", "FIFTHYFOUR", "FOURTYTHREE", "NINE", "TWENTYSEVEN", "THREE", "THIRTEEN", "TWENTYSIX"], "policy": "((\"THIRTYTHREE\" OR (\"FOURTYFIVE\" AND \"SEVENTEEN\")) AND ((\"FOURTEEN\" AND \"FOURTY\") OR ((\"FIFTYTHREEE\" OR \"THIRTYONE\") AND \"SIXTYFOUR\")))"}, {"key": ["FOURTYONE", "FOURTY", "FIVE", "NINE", "TWENTYTWO", "FOURTEEN", "EIGHT", "FOURTYFIVE", "TWENTYSIX", "TWENTYONE", "TWO", "SIXTYTHREE", "THIRTYSIX", "FOURTYTWO", "THIRTY", "ONE", "ELEVEN", "THIRTYTWO", "TWENTYTHREE", "TWENTYNINE", "THIRTYFOUR", "FIFTHYSIX", "FIFTYONE", "SIXTY", "FIFTYTWO", "SIXTYTWO", "FOURTYFOUR", "TWENTYSEVEN", "TWENTYFOUR", "FIFTEEN", "SEVEN", "TWENTY"], "policy": "((((\"THIRTYNINE\" OR \"TWENTYEIGHT\") AND \"TWENTYTHREE\") OR (\"FOURTYFOUR\" AND \"SIXTYFOUR\")) OR (\"FOURTYONE\" AND (\"FOURTY\" AND \"FIVE\")))"}, {"key": ["TWENTYFIVE", "FOUR", "TWELVE", "THIRTYTWO", "FOURTY", "FIFTHYFIVE", "FOURTYNINE", "THIRTYFIVE", "TEN", "ELEVEN", "TWENTYEIGHT", "THIRTYSIX", "FOURTYTHREE", "FIFTHYSIX", "TWENTYTHREE", "FOURTYFIVE", "FIFTHYSEVEN", "THIRTYEIGHT", "SIXTEEN", "FOURTYEIGHT", "SIXTYTHREE", "ONE", "FOURTEEN", "TWENTYSIX", "FIFTYONE", "THIRTYSEVEN", "FIFTYTHREEE", "FIFTEEN", "FIFTHYEIGHT", "THIRTYONE", "FOURTYONE", "FIFTYTWO"], "policy": "((\"EIGHT\" AND \"TWO\") OR ((\"FOURTYSEVEN\" AND (\"THIRTYTWO\" AND \"THREE\")) OR (\"TWENTYFIVE\" AND (\"FOUR\" AND \"TWELVE\"))))"}, {"key": ["FIFTEEN", "TWO", "FIFTYTHREEE", "TWELVE", "FIFTY", "FIFTHYFIVE", "ELEVEN", "FOURTYNINE", "THIRTYEIGHT", "THIRTYFIVE", "FOURTY", "EIGHT", "THIRTYSEVEN", "SIXTY", "TWENTYSIX", "TWENTYEIGHT", "TWENTYTWO", "FOURTYSIX", "FIFTHYSEVEN", "SIXTYONE", "FOURTYONE", "SIXTYFOUR", "THIRTYTHREE", "EIGHTEEN", "TEN", "TWENTYSEVEN", "TWENTYNINE", "SIXTYTWO", "FOURTEEN", "THIRTYNINE", "THIRTYFOUR", "FIFTHYEIGHT"], "policy": "(((\"SIXTYFOUR\" AND \"TWENTYFOUR\") OR (\"FIFTHYNINE\" AND \"SIX\")) OR ((\"TWENTYTWO\" OR \"FOURTYEIGHT\") OR (\"FIFTEEN\" OR \"THIRTYTHREE\")))"}, {"key": ["FOURTYTWO", "FIFTHYEIGHT", "TWENTYEIGHT", "FOURTYEIGHT", "SEVEN", "FOURTYSIX", "THIRTY", "TWENTYONE", "EIGHT", "SIXTYTHREE", "FIFTYTWO", "FIFTY", "THIRTYFOUR", "THIRTEEN", "FIFTYTHREEE", "THIRTYFIVE", "FOURTYNINE", "SIXTYFOUR", "THIRTYNINE", "FOURTYSEVEN", "SIXTYONE", "FOURTY", "TWENTYNINE", "THREE", "FIFTHYSEVEN", "NINETEEN", "FIFTHYNINE", "FOURTYFOUR", "THIRTYTHREE", "THIRTYEIGHT", "TWENTYTWO", "NINE"], "policy": "(((\"THIRTYTHREE\" OR \"THIRTY\") OR (\"TWENTYFOUR\" OR \"FIFTEEN\")) OR ((\"FOURTYTWO\" OR \"TWENTYONE\") AND (\"NINETEEN\" OR \"FIFTHYEIGHT\")))"}, {"key": ["TWENTYTHREE", "FOURTYEIGHT", "SIXTYFOUR", "THREE", "FIFTHYSIX", "THIRTYTHREE", "ELEVEN", "SIXTYTHREE", "SIXTYONE", "FIFTEEN", "EIGHTEEN", "THIRTYONE", "SIXTY", "TWENTYONE", "FOURTYFOUR", "FIFTY", "FIFTHYFOUR", "TWENTYSIX", "FOURTYSIX", "THIRTYSEVEN", "SIXTEEN", "TWENTY", "FIFTHYNINE", "THIRTYFOUR", "FOURTYFIVE", "NINETEEN", "FOUR", "TWO", "THIRTYNINE", "FOURTYSEVEN", "FIFTYTWO", "FIFTYTHREEE"], "policy": "((\"THIRTYNINE\" OR (\"TWENTYSEVEN\" OR (\"THREE\" OR \"SIXTY\"))) OR ((\"TWENTYTHREE\" AND (\"FOURTYEIGHT\" OR \"THIRTYFOUR\")) AND \"SIXTYFOUR\"))"}, {"key": ["EIGHT", "TEN", "THIRTYSEVEN", "FOURTYTWO", "FIFTHYFOUR", "TWENTYEIGHT", "TWENTYONE", "SEVENTEEN", "SIXTYFOUR", "THIRTYFOUR", "THIRTY", "THIRTYONE", "THIRTYTHREE", "THREE", "FIFTHYEIGHT", "FOURTYNINE", "NINETEEN", "TWENTYNINE", "SIXTYONE", "FIFTYTHREEE", "FOURTEEN", "TWO", "FIFTY", "FIVE", "NINE", "FIFTHYFIVE", "TWENTYSEVEN", "FOURTYONE", "SEVEN", "THIRTYEIGHT", "THIRTYNINE", "TWENTYSIX"], "policy": "(((\"EIGHT\" AND \"TEN\") AND \"THIRTYSEVEN\") AND ((\"TWELVE\" OR \"FOURTYTWO\") AND (\"FIFTHYNINE\" OR (\"ELEVEN\" OR \"FIFTHYFOUR\"))))"}, {"key": ["FIFTYTHREEE", "NINE", "TWENTY", "FIFTEEN", "TWENTYFIVE", "FIFTY", "FOURTY", "FOURTYTHREE", "SIXTYTHREE", "FOUR", "FIFTHYFOUR", "THIRTYSIX", "SIXTEEN", "FIFTHYEIGHT", "THIRTYFIVE", "TWENTYSEVEN", "THIRTYEIGHT", "TWO", "ELEVEN", "ONE", "TWENTYSIX", "NINETEEN", "SEVENTEEN", "FOURTYSIX", "THIRTY", "FIFTHYNINE", "SIXTYFOUR", "FIFTHYFIVE", "SIXTYTWO", "FOURTYFIVE", "SIX", "SEVEN"], "policy": "((((\"THIRTYTWO\" AND \"FIFTHYNINE\") OR (\"THIRTYFOUR\" OR \"FOURTEEN\")) OR \"SIXTY\") OR ((\"FIFTYTHREEE\" AND \"NINE\") AND \"TWENTY\"))"}, {"key": ["TWENTYTWO", "THIRTYTWO", "TWENTYSEVEN", "SIXTYTWO", "TWENTYFOUR", "FOURTYSEVEN", "SIXTYFOUR", "FIFTEEN", "TWELVE", "THIRTY", "EIGHT", "THIRTYFOUR", "SIX", "NINE", "FOURTY", "TWENTYNINE", "FOURTYEIGHT", "FIFTHYFOUR", "SEVENTEEN", "FIVE", "THREE", "NINETEEN", "THIRTYONE", "FIFTY", "SIXTYONE", "THIRTYTHREE", "SEVEN", "TWENTY", "SIXTYTHREE", "THIRTYFIVE", "FOURTYONE", "TWENTYONE"], "policy": "((\"TWENTYEIGHT\" AND (\"FIFTHYSEVEN\" AND (\"SIXTYTHREE\" OR \"THIRTEEN\"))) OR ((\"SIX\" OR (\"FIFTHYFIVE\" OR \"TWENTYTWO\")) AND \"THIRTYTWO\"))"}, {"key": ["SIXTYFOUR", "TWO", "FIFTHYNINE", "FIFTHYSIX", "NINE", "THIRTYONE", "THIRTYSEVEN", "SIXTY", "TWENTYONE", "SIXTYTHREE", "SIXTYONE", "TWELVE", "FOURTY", "FIFTYONE", "FIFTEEN", "THIRTY", "TWENTYEIGHT", "FIFTYTWO", "NINETEEN", "FOURTYTWO", "TWENTYNINE", "FOURTYSIX", "SEVENTEEN", "SEVEN", "FIFTHYFIVE", "SIXTYTWO", "EIGHTEEN", "SIXTEEN", "FIFTHYSEVEN", "FIFTHYFOUR", "FOURTYFIVE", "FIFTHYEIGHT"], "policy": "(((\"SIXTYFOUR\" OR (\"FIFTYTHREEE\" AND \"FIFTHYSEVEN\")) OR (\"SIXTYTWO\" OR \"SEVENTEEN\")) AND (\"SIXTEEN\" OR (\"TWO\" AND \"FIFTHYNINE\")))"}, {"key": ["FIFTHYFIVE", "THIRTYTWO", "THIRTYEIGHT", "FOURTY", "TWENTYFOUR", "FIFTYONE", "FIFTHYEIGHT", "FOURTEEN", "SIXTYONE", "THIRTY", "TWENTYFIVE", "FIFTHYFOUR", "ONE", "FOURTYNINE", "SIX", "TWENTYTHREE", "TWENTYNINE", "THIRTYSIX", "TWO", "FOURTYONE", "FOUR", "TWENTYTWO", "SEVEN", "SIXTYFOUR", "SEVENTEEN", "FOURTYSEVEN", "THIRTYONE", "THIRTYFIVE", "FIFTY", "FIFTEEN", "EIGHT", "THIRTYTHREE"], "policy": "((\"THIRTYSEVEN\" OR (\"TWELVE\" OR \"FOURTYSEVEN\")) OR (((\"FIFTHYFIVE\" AND \"THIRTYTWO\") OR \"NINE\") AND (\"THIRTYEIGHT\" AND \"FOURTY\")))"}, {"key": ["SIXTEEN", "TWENTYONE", "TWENTYFIVE", "THIRTY", "TWENTYTHREE", "FIVE", "SEVEN", "SIXTY", "FOURTYONE", "TWELVE", "FOURTYFIVE", "SEVENTEEN", "FOURTYFOUR", "TWENTYFOUR", "FIFTHYFOUR", "THIRTYSIX", "ELEVEN", "TWENTYTWO", "THIRTYONE", "TWENTYNINE", "FOURTYTWO", "SIXTYONE", "NINE", "TEN", "FOUR", "FIFTYTWO", "THIRTYTHREE", "FIFTHYNINE", "SIXTYFOUR", "FOURTYEIGHT", "FIFTYTHREEE", "FIFTEEN"], "policy": "((((\"SIXTEEN\" AND \"TWENTYONE\") AND \"TWENTYFIVE\") AND (\"THIRTY\" AND \"TWENTYTHREE\")) AND ((\"FIVE\" AND \"SEVEN\") AND \"SIXTY\"))"}, {"key": ["SIXTEEN", "SEVENTEEN", "SIXTYTWO", "FIFTHYFIVE", "FIVE", "THIRTEEN", "FIFTEEN", "TWENTYTWO", "SIXTYTHREE", "SIXTYFOUR", "NINE", "FOURTYTWO", "SIXTY", "FOURTYFOUR", "FIFTHYEIGHT", "SIXTYONE", "FOURTYEIGHT", "TWENTYONE", "ONE", "ELEVEN", "FIFTYTWO", "FIFTYTHREEE", "THIRTYTWO", "FIFTY", "FOURTYSEVEN", "EIGHTEEN", "TWENTYSEVEN", "TWENTYNINE", "FIFTHYSIX", "TEN", "FIFTHYFOUR", "THIRTYFIVE"], "policy": "((\"SIXTEEN\" AND \"SEVENTEEN\") AND ((((\"SIXTYTHREE\" AND \"FIFTEEN\") OR \"SIXTYTWO\") AND \"FIFTHYFIVE\") OR (\"EIGHT\" OR \"THIRTYEIGHT\")))"}, {"key": ["SIXTYONE", "SIXTYTWO", "TWENTYFOUR", "FOURTYFOUR", "FIFTYTWO", "ONE", "ELEVEN", "FOURTYTHREE", "THIRTYFOUR", "THIRTYSEVEN", "FOURTYFIVE", "FIFTHYSIX", "FOURTY", "FIFTY", "FIVE", "THIRTYNINE", "THIRTYSIX", "TWENTYTWO", "TWENTYTHREE", "FIFTHYFIVE", "THREE", "TWO", "THIRTEEN", "EIGHTEEN", "FOURTEEN", "NINE", "FIFTEEN", "TEN", "THIRTYTHREE", "TWENTYEIGHT", "THIRTYTWO", "SIXTYTHREE"], "policy": "(((\"SIXTYONE\" OR \"FIFTYTHREEE\") OR (\"TWENTYEIGHT\" OR \"FOURTY\")) AND ((\"TWENTY\" OR \"THIRTYFOUR\") OR (\"SIXTYTWO\" AND \"TWENTYFOUR\")))"}, {"key": ["THIRTYSIX", "SIXTYTHREE", "FIFTHYFIVE", "ELEVEN", "FIFTHYFOUR", "SIXTYONE", "TWENTYTWO", "EIGHTEEN", "FOURTYSIX", "TWENTYEIGHT", "THIRTYTHREE", "SIXTYTWO", "THIRTEEN", "FOURTYONE", "TWENTY", "THIRTYSEVEN", "TWENTYTHREE", "TWENTYFOUR", "ONE", "TWENTYSEVEN", "FOUR", "SEVEN", "FOURTY", "SIXTEEN", "FIFTYTHREEE", "FIFTEEN", "FIFTYONE", "TWENTYNINE", "SIXTYFOUR", "FIFTY", "TWELVE", "THIRTYFOUR"], "policy": "(((\"THIRTYSIX\" OR \"FIFTEEN\") AND (\"SIXTYTWO\" OR \"SIXTYTHREE\")) AND ((\"FIFTHYEIGHT\" AND \"THIRTYTWO\") OR (\"FIFTHYFIVE\" AND \"ELEVEN\")))"}, {"key": ["SEVEN", "FIFTYTWO", "TWENTYNINE", "ELEVEN", "TWELVE", "THIRTYEIGHT", "FOURTYFIVE", "TWENTYTWO", "FIFTHYFIVE", "FIFTHYSEVEN", "FOURTYSEVEN", "THIRTY", "THIRTEEN", "THIRTYTHREE", "FOURTYFOUR", "TWENTYSEVEN", "SIXTYTHREE", "TEN", "FOUR", "SIXTYONE", "TWENTYEIGHT", "FIFTY", "THREE", "FOURTYTHREE", "FIVE", "FIFTYONE", "FIFTYTHREEE", "SIXTEEN", "TWENTYSIX", "SIXTYFOUR", "FOURTYEIGHT", "THIRTYTWO"], "policy": "(((\"SEVEN\" OR (\"SIXTEEN\" OR \"THIRTYEIGHT\")) AND (\"FIFTYTWO\" AND \"TWENTYNINE\")) OR (\"FOURTYFIVE\" AND (\"ELEVEN\" AND \"THIRTYSEVEN\")))"}, {"key": ["FOUR", "TWELVE", "THIRTEEN", "FIFTHYFOUR", "SIX", "THIRTYEIGHT", "TWENTYFIVE", "THIRTYTHREE", "SIXTYFOUR", "FIFTYTHREEE", "THIRTYSEVEN", "NINETEEN", "THIRTYNINE", "FIFTHYSEVEN", "FOURTY", "SIXTYTWO", "FOURTYFOUR", "THIRTYFOUR", "NINE", "FOURTYEIGHT", "SIXTYTHREE", "SIXTY", "THIRTYFIVE", "TWO", "EIGHT", "FIFTYTWO", "FOURTYTWO", "THIRTYTWO", "FIVE", "FIFTEEN", "ONE", "FIFTY"], "policy": "(((\"TEN\" AND \"NINE\") OR \"FOUR\") AND ((\"TWELVE\" AND \"THIRTEEN\") AND (\"TWENTYFIVE\" OR (\"ELEVEN\" OR \"FIFTHYFOUR\"))))"}, {"key": ["EIGHT", "FOURTYFIVE", "TWENTYFIVE", "ONE", "FIFTEEN", "SIXTYONE", "TWO", "SIXTEEN", "TWENTY", "TWENTYEIGHT", "FOURTYSIX", "TWENTYSEVEN", "EIGHTEEN", "FIFTHYSEVEN", "THIRTYEIGHT", "THIRTYONE", "FOURTYTHREE", "FIFTY", "FIFTHYEIGHT", "THIRTYTWO", "TWENTYTHREE", "SEVENTEEN", "FIFTHYFIVE", "ELEVEN", "SEVEN", "THIRTYSEVEN", "FIFTYTHREEE", "FOURTYTWO", "FIVE", "FOURTYSEVEN", "SIXTYTHREE", "TWENTYSIX"], "policy": "(((\"TWENTYTHREE\" OR \"SEVEN\") OR (\"EIGHT\" AND \"FOURTYFIVE\")) AND ((\"THIRTYTHREE\" AND \"FIFTHYEIGHT\") OR (\"TWENTYFIVE\" AND \"ONE\")))"}, {"key": ["FIFTYONE", "SIXTY", "THIRTYNINE", "FOURTYONE", "FOURTYFIVE", "THIRTYFOUR", "FIVE", "FIFTHYSEVEN", "THIRTYSIX", "FIFTHYFOUR", "FIFTHYNINE", "TEN", "THIRTYTHREE", "TWENTYTWO", "ONE", "TWO", "THIRTYEIGHT", "SIXTYFOUR", "THIRTYSEVEN", "FOURTYTWO", "FOUR", "SEVENTEEN", "FOURTY", "THREE", "THIRTYFIVE", "EIGHTEEN", "SIXTYTHREE", "FOURTYTHREE", "SIXTYTWO", "FOURTYSIX", "TWENTYONE", "FOURTEEN"], "policy": "(((\"FIFTYONE\" AND (\"FOURTYTHREE\" OR \"SIXTY\")) OR (\"FOURTYTWO\" AND (\"FOURTYSIX\" AND \"EIGHT\"))) OR (\"TWENTYNINE\" AND \"TWELVE\"))"}, {"key": ["TWO", "SIX", "THIRTEEN", "FOURTYFOUR", "THIRTYFIVE", "FIFTHYFIVE", "TWENTYONE", "TWENTYFOUR", "SIXTYTHREE", "THREE", "FIFTY", "TWENTYNINE", "THIRTYONE", "FIFTHYFOUR", "FOURTYNINE", "NINE", "EIGHTEEN", "FOURTYFIVE", "FIFTHYNINE", "ELEVEN", "SIXTYFOUR", "FOURTYSIX", "SIXTYTWO", "SEVENTEEN", "FOURTY", "ONE", "TWENTYSEVEN", "FIVE", "THIRTYTHREE", "FOURTYTHREE", "THIRTY", "THIRTYTWO"], "policy": "(((\"TWENTYTHREE\" OR \"THIRTYTWO\") AND (\"FIFTHYNINE\" AND \"THIRTYTHREE\")) OR ((\"TWENTYEIGHT\" OR \"TWENTYFIVE\") OR (\"TWO\" AND \"SIX\")))"}]