[{"policy": "((((\"THIRTYONE\" and ((\"FIFTHYSEVEN\" and \"TWENTYONE\") or \"TWENTYFIVE\")) or ((\"NINE\" or ((\"FOURTYFOUR\" or \"TWELVE\") and \"EIGHTEEN\")) and \"SIXTYTHREE\")) or (((\"SIXTYONE\" and \"TWENTYNINE\") and (\"FIFTYTHREEE\" and \"FOURTYFIVE\")) or (\"FIFTHYFIVE\" or (\"THIRTYEIGHT\" or \"THIRTEEN\")))) and ((((\"SIXTY\" and \"TWENTYSIX\") or (\"THIRTYTWO\" and \"EIGHT\")) or ((\"SIXTYFOUR\" or \"FOURTY\") or (((\"FOURTYTWO\" and \"FOURTYTHREE\") or \"ONE\") and (\"FIFTHYFOUR\" and \"FOUR\")))) or ((\"TEN\" or (\"TWENTY\" or \"SIXTYTWO\")) or (\"FIFTY\" and \"FOURTYEIGHT\"))))", "key": ["SIXTYONE", "TWENTYNINE", "FIFTYTHREEE", "FOURTYFIVE", "TEN", "FIFTHYSIX", "ONE", "SEVEN", "FIVE", "THIRTYEIGHT", "EIGHTEEN", "SIX", "FIFTEEN", "TWENTYTHREE", "ELEVEN", "FOURTYSEVEN", "THIRTYFIVE", "TWENTYFOUR", "FIFTYONE", "THIRTYONE", "TWENTYFIVE", "THIRTYFOUR", "FOURTY", "SIXTYTWO", "TWENTYTWO", "THIRTYTHREE", "SIXTYTHREE", "THIRTYSEVEN", "FIFTY", "THIRTYNINE", "THIRTYTWO", "THIRTEEN"]}, {"policy": "(((\"THIRTYSIX\" or (\"FIFTYTWO\" and ((\"TWENTYTWO\" and \"FOURTYFIVE\") or (\"EIGHT\" or \"SIXTEEN\")))) or (((\"THREE\" and (\"THIRTYEIGHT\" or \"TWENTYSIX\")) and (\"TWENTY\" and \"NINE\")) or ((\"SIX\" or (\"THIRTY\" and \"THIRTYTHREE\")) and (\"SIXTYTHREE\" and \"SEVENTEEN\")))) and (((((\"TWENTYONE\" and \"FIFTHYNINE\") or \"TWELVE\") and \"NINETEEN\") or ((\"FIFTHYSEVEN\" or \"FIFTHYFIVE\") or (\"SIXTYTWO\" or \"THIRTYFIVE\"))) and ((\"FOURTYFOUR\" and ((\"FOURTYSEVEN\" or \"TWENTYFOUR\") or ((\"ELEVEN\" and \"TWENTYFIVE\") and \"FOURTYONE\"))) and (\"FOUR\" and \"FIFTHYEIGHT\"))))", "key": ["THIRTY", "THIRTYTHREE", "SIXTYTHREE", "SEVENTEEN", "FIFTHYFIVE", "FOURTYFOUR", "FOURTYSEVEN", "FOUR", "FIFTHYEIGHT", "FOURTYNINE", "TWO", "SIXTEEN", "THIRTYSIX", "TWENTYFIVE", "THIRTYNINE", "FOURTYONE", "TWENTYEIGHT", "SIXTYONE", "FIFTHYSIX", "EIGHT", "THIRTYFOUR", "FIFTYONE", "TWENTYNINE", "EIGHTEEN", "NINE", "TWENTYTWO", "FOURTYTHREE", "FOURTEEN", "SEVEN", "FOURTYTWO", "SIXTYTWO", "THREE"]}, {"policy": "((((\"TWENTY\" or ((\"FIFTEEN\" or \"TWENTYSIX\") and ((\"FIFTYTHREEE\" and \"FIFTY\") or (\"FOURTY\" and \"TWENTYTHREE\")))) and (\"ELEVEN\" or (\"FOURTYTHREE\" and \"THIRTYFIVE\"))) and (((((\"SEVEN\" and \"TWENTYTWO\") and \"FIFTHYFOUR\") or \"THIRTYTWO\") or (\"TEN\" or (\"THIRTYEIGHT\" and \"FIFTHYSIX\"))) or (\"FOURTYSEVEN\" and (\"FIFTYONE\" and (\"SIXTYTHREE\" and \"THIRTYSIX\"))))) and ((((\"THIRTYFOUR\" and \"SIXTEEN\") or \"SIXTYONE\") and (\"FOURTYEIGHT\" and \"TWENTYNINE\")) and (((\"FIFTHYSEVEN\" or (\"THIRTYSEVEN\" and \"THIRTYONE\")) or \"FIFTHYEIGHT\") and (\"TWENTYONE\" or \"TWENTYEIGHT\"))))", "key": ["FIFTEEN", "FIFTYTHREEE", "FIFTY", "FOURTYTHREE", "THIRTYFIVE", "THIRTYTWO", "THIRTYFOUR", "SIXTEEN", "FOURTYEIGHT", "TWENTYNINE", "FIFTHYSEVEN", "TWENTYEIGHT", "FIFTYTWO", "SIXTYONE", "FIFTHYFOUR", "FOURTYNINE", "SIXTYFOUR", "THIRTEEN", "FIFTYONE", "TWELVE", "FIVE", "ELEVEN", "TWENTYSIX", "FOURTYSIX", "THIRTYNINE", "THREE", "FIFTHYEIGHT", "THIRTYONE", "FOURTYFOUR", "NINE", "NINETEEN", "THIRTYSIX"]}, {"policy": "((((((\"TWO\" and \"FIFTHYSIX\") and \"THIRTY\") and (\"THIRTEEN\" or \"TWENTYFIVE\")) and ((\"TWENTYSIX\" or \"FIFTHYEIGHT\") and ((\"THIRTYSIX\" and \"FIFTEEN\") or \"TWENTYTHREE\"))) and (((\"NINE\" and \"FIFTHYFIVE\") and \"TWENTYONE\") and ((\"SIXTYONE\" and \"SIXTYTWO\") or (\"FOUR\" and (\"EIGHT\" and \"THIRTYNINE\"))))) and ((((\"THIRTYEIGHT\" or \"NINETEEN\") or \"SIXTYTHREE\") and (((\"ONE\" or \"SIXTEEN\") or \"FOURTYFOUR\") and (\"THIRTYTHREE\" and \"TWENTYNINE\"))) and (((\"THIRTYFIVE\" and \"FIFTHYNINE\") and (\"FOURTYFIVE\" and \"FIFTYTHREEE\")) or (\"FIVE\" or \"TWENTY\"))))", "key": ["TWO", "FIFTHYSIX", "THIRTY", "TWENTYFIVE", "FIFTHYEIGHT", "THIRTYSIX", "FIFTEEN", "NINE", "FIFTHYFIVE", "TWENTYONE", "FOUR", "EIGHT", "THIRTYNINE", "THIRTYEIGHT", "FOURTYFOUR", "THIRTYTHREE", "TWENTYNINE", "THIRTYFIVE", "FIFTHYNINE", "FOURTYFIVE", "FIFTYTHREEE", "SIXTEEN", "THIRTYSEVEN", "TWELVE", "FIFTY", "TWENTYTHREE", "FOURTYONE", "SIXTYONE", "SIXTYFOUR", "EIGHTEEN", "SIX", "FOURTEEN"]}, {"policy": "((((\"TWENTYFOUR\" and \"FIFTYONE\") and ((\"SIX\" and \"ELEVEN\") and ((\"TWENTYSEVEN\" or \"TWENTYEIGHT\") and \"THIRTYNINE\"))) and (((\"FOURTYONE\" or \"FIFTHYEIGHT\") or (\"TWELVE\" or \"SIXTYTHREE\")) and (\"FIFTHYFIVE\" or (\"SEVENTEEN\" and (\"FIFTHYSIX\" or \"FOURTYFOUR\"))))) and (((\"THIRTYTHREE\" and (\"FOURTYSEVEN\" or \"FOUR\")) or \"FOURTYSIX\") or (((\"FIFTHYNINE\" and (\"TWENTYFIVE\" or (\"FOURTYTHREE\" or \"TWENTYONE\"))) and ((\"FOURTYNINE\" and (\"FOURTY\" and \"FIFTEEN\")) or \"FIVE\")) and (\"THREE\" or (\"SIXTEEN\" or (\"THIRTYTWO\" and (\"ONE\" and \"THIRTYFOUR\")))))))", "key": ["TWENTYFOUR", "FIFTYONE", "SIX", "ELEVEN", "TWENTYSEVEN", "THIRTYNINE", "FOURTYONE", "SEVENTEEN", "FOURTYFOUR", "FIFTHYNINE", "TWENTYFIVE", "FIVE", "THREE", "THIRTYEIGHT", "FOURTYFIVE", "NINE", "THIRTY", "SIXTYFOUR", "THIRTYSEVEN", "FOURTYNINE", "SEVEN", "FIFTHYSEVEN", "FOUR", "TWENTYONE", "THIRTYFOUR", "EIGHT", "THIRTEEN", "SIXTEEN", "TWENTYTHREE", "FOURTEEN", "SIXTY", "EIGHTEEN"]}, {"policy": "(((((\"TWENTYNINE\" and \"FOUR\") and (\"FIFTY\" or \"FIVE\")) or ((\"FIFTHYNINE\" or \"SEVEN\") and ((\"FIFTYTWO\" or \"FIFTHYSIX\") or (\"SIXTY\" or \"THIRTYSEVEN\")))) and ((\"FOURTEEN\" or \"FOURTYONE\") or ((\"TWENTYTHREE\" or \"TWENTYONE\") and \"NINETEEN\"))) or ((((\"TWENTYSIX\" and \"SEVENTEEN\") and \"SIXTYFOUR\") or ((\"TEN\" or (\"THIRTYNINE\" and \"FIFTHYFOUR\")) and (\"FOURTYSIX\" and \"FOURTYNINE\"))) or ((((\"TWO\" and \"FOURTYFOUR\") or \"FIFTHYFIVE\") and \"ONE\") and (((\"EIGHTEEN\" or \"SIX\") or (\"FOURTYTWO\" and \"NINE\")) and \"THIRTYTHREE\"))))", "key": ["TWENTYNINE", "FOUR", "FIFTY", "TWENTYONE", "NINETEEN", "FOURTY", "SIXTEEN", "FOURTYONE", "FOURTYEIGHT", "THIRTYNINE", "SIX", "THIRTEEN", "TWELVE", "FOURTYFIVE", "FIFTHYEIGHT", "FOURTYSIX", "THIRTYSEVEN", "FOURTYSEVEN", "FOURTYNINE", "ONE", "NINE", "FIFTYTHREEE", "SIXTYFOUR", "TWO", "FIVE", "TWENTYTHREE", "THIRTYONE", "TWENTYTWO", "FOURTYTHREE", "FOURTYTWO", "FIFTHYSIX", "SIXTYTHREE"]}, {"policy": "((((\"SIXTEEN\" and \"FIFTHYEIGHT\") and (\"FIFTYTHREEE\" or ((\"ONE\" or (\"TWENTYNINE\" and \"TWENTYTWO\")) and \"FOURTYSEVEN\"))) and ((\"FIFTY\" and \"TEN\") or ((\"FOURTYNINE\" and ((\"FOURTYFOUR\" and \"SIXTYTHREE\") and (\"NINETEEN\" and \"FIFTHYFOUR\"))) or (\"FOURTYEIGHT\" or (\"FIVE\" or (\"ELEVEN\" or \"THIRTYONE\")))))) or (((((\"FIFTHYNINE\" or \"SIXTYONE\") and \"THIRTEEN\") and \"FOURTEEN\") and ((\"EIGHT\" and \"TWENTYSEVEN\") and (\"NINE\" or \"THIRTYTWO\"))) or ((\"TWENTYFIVE\" and (\"FOUR\" or (\"FIFTYTWO\" or \"THIRTYFOUR\"))) or (\"TWENTYEIGHT\" or \"FIFTHYSIX\"))))", "key": ["FIFTHYSIX", "FIFTYONE", "SEVEN", "FIFTHYSEVEN", "TWO", "SIXTYTHREE", "TWELVE", "EIGHTEEN", "FIFTYTWO", "THIRTYSIX", "FIFTEEN", "TWENTYTHREE", "TWENTY", "TWENTYONE", "THIRTYFIVE", "TWENTYFIVE", "FOURTYTHREE", "THIRTYTWO", "TWENTYSIX", "FOURTEEN", "EIGHT", "ELEVEN", "NINETEEN", "TWENTYEIGHT", "THREE", "THIRTEEN", "THIRTYEIGHT", "FOURTYTWO", "THIRTYNINE", "SIXTEEN", "SEVENTEEN", "FOURTY"]}, {"policy": "((((((\"TWENTYTHREE\" or \"SIXTYFOUR\") and \"FIFTHYEIGHT\") and (\"FOUR\" and (\"FIFTHYNINE\" and \"SEVEN\"))) and ((\"TEN\" and \"EIGHTEEN\") or (\"TWENTYNINE\" or \"TWENTYEIGHT\"))) and ((((\"NINETEEN\" or \"TWO\") or (\"FOURTYSIX\" and \"THREE\")) and ((\"THIRTY\" and \"FOURTYEIGHT\") or \"FOURTEEN\")) or ((\"SIXTYTWO\" and \"EIGHT\") or \"TWENTYSEVEN\"))) or ((((\"THIRTYFOUR\" and \"THIRTYSEVEN\") and \"SIX\") or (((\"TWELVE\" or \"THIRTYEIGHT\") and \"FIFTHYSEVEN\") and (\"FIFTY\" and \"THIRTEEN\"))) and (\"FIFTYTWO\" or (\"FOURTYTWO\" or (\"FOURTYONE\" and \"THIRTYFIVE\")))))", "key": ["THIRTYEIGHT", "FIFTHYSEVEN", "FIFTY", "THIRTEEN", "FIFTYTWO", "FOURTYFOUR", "FOURTYTHREE", "TWENTYTHREE", "FOURTEEN", "SIXTEEN", "TWENTYONE", "FOURTYSIX", "FOUR", "ONE", "TWO", "TEN", "FIFTEEN", "TWENTYFOUR", "THIRTYNINE", "FIFTYTHREEE", "TWENTYFIVE", "SEVENTEEN", "FIFTYONE", "NINETEEN", "TWENTYEIGHT", "SIXTYONE", "SIXTYTHREE", "THIRTYTHREE", "THIRTYONE", "TWENTYSEVEN", "FOURTY", "FIFTHYEIGHT"]}, {"policy": "(((((\"THIRTYFIVE\" or \"THIRTYSEVEN\") and ((\"FOURTYFIVE\" or \"TWENTYTHREE\") and (\"SIXTYONE\" or \"THIRTYEIGHT\"))) and ((\"SIX\" or \"TWENTYSEVEN\") or \"SEVENTEEN\")) or (((\"FIFTHYEIGHT\" and \"THIRTYTWO\") or (\"TWENTYONE\" and (\"THIRTYTHREE\" and \"SIXTY\"))) and (((\"FIFTY\" and \"FIFTHYFIVE\") or (\"TWENTYFIVE\" or \"TWO\")) and \"SIXTYTWO\"))) and (((\"FOURTYEIGHT\" and \"THIRTY\") and (\"FOURTYNINE\" or \"FOURTYTWO\")) or ((\"SIXTEEN\" and ((\"FIVE\" or \"FOURTYFOUR\") or (\"FOURTYTHREE\" and \"TEN\"))) and (\"ONE\" or ((\"EIGHTEEN\" or \"TWENTY\") or \"FOURTYSIX\")))))", "key": ["TWENTYONE", "THIRTYTHREE", "SIXTY", "TWO", "SIXTYTWO", "FOURTYEIGHT", "THIRTY", "FOURTYTWO", "TWENTYFOUR", "SIXTYTHREE", "THIRTYEIGHT", "FOURTYTHREE", "FIFTEEN", "FOURTY", "FIFTYTHREEE", "FIFTHYFIVE", "FIVE", "SEVEN", "FIFTHYSIX", "TWENTYEIGHT", "TEN", "NINETEEN", "TWENTYSIX", "TWENTYTWO", "FOURTYFOUR", "THIRTEEN", "ONE", "THIRTYFOUR", "FOURTYNINE", "TWENTYTHREE", "TWENTYSEVEN", "TWELVE"]}, {"policy": "((((((\"FOURTYFIVE\" and \"FIFTY\") and \"SIXTYFOUR\") or (\"SEVEN\" or \"FIFTYONE\")) and ((\"FOURTYFOUR\" and \"THIRTEEN\") and (\"TWENTYTHREE\" and \"FIFTEEN\"))) and ((((\"FIFTHYSIX\" or \"FOURTYONE\") or ((\"FIFTHYEIGHT\" or \"SIXTEEN\") and \"ONE\")) or (\"SIX\" or \"NINETEEN\")) or (\"SIXTYTWO\" and \"FOUR\"))) and (((\"FIFTHYFOUR\" or ((\"THIRTYTHREE\" and \"FOURTYSEVEN\") or \"SIXTY\")) or (\"ELEVEN\" and (\"FIFTHYFIVE\" or \"SIXTYONE\"))) or (((\"THREE\" or (\"THIRTY\" and \"FIVE\")) and (\"FIFTYTHREEE\" or (\"TWENTYEIGHT\" and \"EIGHT\"))) and \"FOURTYTHREE\")))", "key": ["FOURTYFIVE", "FIFTY", "SIXTYFOUR", "FOURTYFOUR", "THIRTEEN", "TWENTYTHREE", "FIFTEEN", "SIXTYTWO", "FOUR", "THREE", "TWENTYEIGHT", "EIGHT", "FOURTYTHREE", "FOURTY", "THIRTYFOUR", "TWO", "THIRTYEIGHT", "FOURTEEN", "FOURTYSEVEN", "THIRTYSIX", "TWENTYONE", "FOURTYNINE", "TWENTY", "FIFTHYNINE", "SEVEN", "TWENTYTWO", "THIRTYNINE", "FIFTYONE", "THIRTYFIVE", "SIXTYTHREE", "EIGHTEEN", "FIFTHYFOUR"]}, {"policy": "(((((\"TEN\" or \"TWENTY\") and \"ONE\") or (((\"THIRTYNINE\" or \"FOUR\") or \"FOURTYSEVEN\") and \"SIXTEEN\")) and ((\"EIGHT\" or \"SIX\") and (\"FOURTYFIVE\" or (\"THIRTYTWO\" and \"FOURTYONE\")))) or (((((\"TWELVE\" and \"FIFTHYFIVE\") and \"NINE\") and (\"FOURTYTWO\" and (\"FIFTEEN\" or \"TWENTYSIX\"))) and ((\"NINETEEN\" and \"THREE\") and (\"SIXTYTHREE\" and (\"THIRTY\" or \"THIRTYFOUR\")))) or ((\"FIFTHYFOUR\" and \"THIRTYSIX\") and (((\"TWENTYFIVE\" and \"TWENTYONE\") or ((\"FIFTYTHREEE\" and \"TWENTYSEVEN\") or \"SEVENTEEN\")) or (\"FIVE\" or \"TWENTYFOUR\")))))", "key": ["TWELVE", "FIFTHYFIVE", "NINE", "FOURTYTWO", "TWENTYSIX", "NINETEEN", "THREE", "SIXTYTHREE", "THIRTYFOUR", "SIXTYFOUR", "THIRTYSEVEN", "THIRTYTWO", "SIXTY", "TEN", "FIFTEEN", "SEVEN", "FOURTYEIGHT", "TWENTYFIVE", "TWO", "TWENTY", "SIXTEEN", "THIRTYNINE", "TWENTYEIGHT", "THIRTY", "THIRTYTHREE", "FOURTYFOUR", "FIFTYTWO", "FIFTYTHREEE", "SIXTYTWO", "FOURTYONE", "FOURTYSEVEN", "FIFTHYNINE"]}, {"policy": "((((((\"SIXTYONE\" or (\"ELEVEN\" and \"FOURTY\")) and \"FOURTYTWO\") or ((\"TWENTYNINE\" and (\"TWO\" and \"TWENTYONE\")) or \"EIGHTEEN\")) and (((\"THREE\" or \"FIVE\") or \"FOURTYSIX\") or ((\"FIFTHYEIGHT\" and \"SIXTY\") and ((\"SIXTYTHREE\" and \"ONE\") and \"SIX\")))) and (((\"THIRTEEN\" and \"FOURTYONE\") and \"THIRTYFIVE\") or \"FOURTYFIVE\")) or ((((\"FOURTYEIGHT\" and \"TWENTYSEVEN\") and \"EIGHT\") or ((\"THIRTY\" or (\"TWENTY\" or \"THIRTYTWO\")) or \"THIRTYEIGHT\")) and ((\"FOURTYSEVEN\" or \"SIXTYTWO\") and (\"NINE\" and (\"TWELVE\" and \"THIRTYTHREE\")))))", "key": ["EIGHTEEN", "THREE", "FOURTYFIVE", "FIFTEEN", "SIX", "FIFTHYSEVEN", "TWENTYFOUR", "TEN", "FOURTYONE", "FIFTYTWO", "SIXTYFOUR", "TWELVE", "FOURTY", "THIRTYONE", "SIXTYTWO", "FOURTYNINE", "TWENTYSEVEN", "SIXTY", "NINE", "SEVEN", "TWENTYNINE", "TWENTYFIVE", "FOURTEEN", "FIFTYTHREEE", "TWO", "FIVE", "FOURTYTHREE", "FIFTHYFIVE", "THIRTY", "THIRTYEIGHT", "TWENTYTWO", "FOURTYEIGHT"]}, {"policy": "(((((\"TWELVE\" or (\"FIFTYTHREEE\" or (\"FOUR\" or \"FIFTHYFOUR\"))) and (\"FOURTYFIVE\" or \"FOURTEEN\")) and (\"FOURTYSIX\" and (\"SIXTY\" or (\"ONE\" or \"TWENTYFIVE\")))) and (((\"THIRTYTHREE\" and \"TWO\") and (\"FIFTYTWO\" or \"FOURTYNINE\")) and ((\"SIX\" or \"THIRTYSEVEN\") and \"FOURTYFOUR\"))) or ((((((\"FIFTY\" and \"THIRTYONE\") or \"FOURTYEIGHT\") and (\"FIVE\" or (\"THIRTEEN\" or \"FIFTHYEIGHT\"))) and \"ELEVEN\") and ((\"SIXTYFOUR\" or \"THIRTYTWO\") or (\"TWENTYTHREE\" or \"THIRTYSIX\"))) and (((\"FIFTHYSEVEN\" and \"EIGHTEEN\") and \"SEVENTEEN\") or \"FIFTYONE\")))", "key": ["TWELVE", "FOURTYFIVE", "FOURTYSIX", "ONE", "THIRTYTHREE", "TWO", "FOURTYNINE", "SIX", "FOURTYFOUR", "FIFTHYSIX", "FIFTYONE", "FOURTYEIGHT", "FOUR", "FOURTYSEVEN", "FIFTHYFOUR", "THIRTEEN", "FIFTHYEIGHT", "NINE", "FOURTYONE", "THIRTY", "THIRTYFIVE", "FIFTEEN", "FIFTHYFIVE", "THIRTYSEVEN", "THIRTYONE", "SIXTYONE", "FOURTEEN", "TWENTYTWO", "SEVEN", "TWENTYFOUR", "FIFTY", "NINETEEN"]}, {"policy": "((((\"FOUR\" or (\"NINETEEN\" and \"FOURTYFIVE\")) and (((\"FIFTEEN\" and \"FIFTHYSIX\") or \"THIRTYEIGHT\") or (\"FOURTYSIX\" or \"SIXTYTWO\"))) and ((((\"TWELVE\" and \"EIGHTEEN\") and \"ELEVEN\") and (\"THIRTY\" and \"TWENTYTWO\")) or (\"FIFTY\" and (((\"FIFTHYNINE\" or \"SIXTYTHREE\") or \"SIXTYONE\") or \"TWENTYNINE\")))) and (((\"THIRTYFOUR\" or \"FOURTYNINE\") or ((\"FIFTYONE\" or (\"FOURTYFOUR\" or \"FIVE\")) or (\"FOURTEEN\" or \"FIFTHYFOUR\"))) or (((\"TWENTYFIVE\" or \"SIXTYFOUR\") or \"EIGHT\") and ((\"FIFTHYEIGHT\" and \"FIFTHYFIVE\") or (\"TWENTYTHREE\" or \"TWENTYSIX\")))))", "key": ["NINETEEN", "FOURTYFIVE", "SIXTYTWO", "FIFTY", "SIXTYTHREE", "FIFTHYFOUR", "FIFTHYFIVE", "EIGHTEEN", "FIFTYTHREEE", "TWENTYEIGHT", "FOURTY", "TWENTYTHREE", "TWELVE", "TEN", "FIFTEEN", "TWENTYONE", "THIRTYONE", "THIRTYSIX", "ELEVEN", "SEVEN", "THIRTEEN", "SIXTYFOUR", "THIRTYTHREE", "FIFTYTWO", "FOURTYSEVEN", "SIXTYONE", "NINE", "FIFTHYNINE", "FIFTHYEIGHT", "TWENTYSEVEN", "SIXTY", "FOUR"]}, {"policy": "(((((\"FOURTYNINE\" or (\"FIVE\" or (\"FIFTHYEIGHT\" or \"ELEVEN\"))) and (\"TWENTYSEVEN\" or \"FIFTHYSIX\")) and ((\"FOURTYEIGHT\" and \"THIRTYFIVE\") and (\"FIFTHYNINE\" or \"FOURTYONE\"))) and ((\"SEVENTEEN\" or \"THIRTYNINE\") or ((\"FOURTYTHREE\" and \"TWENTYONE\") or (\"THREE\" and \"FIFTYTHREEE\")))) and ((\"ONE\" and (((\"FOURTYFIVE\" and \"THIRTYEIGHT\") and (\"TWENTYEIGHT\" and \"FIFTHYFIVE\")) and (\"EIGHT\" or \"THIRTYTHREE\"))) and (((\"TWENTYFIVE\" and \"SIXTYONE\") or (\"TWENTYNINE\" or (\"SIX\" or \"TWENTYFOUR\"))) and ((\"TWELVE\" or \"TWENTY\") or (\"THIRTYFOUR\" and \"THIRTYONE\")))))", "key": ["FOURTYNINE", "TWENTYSEVEN", "FOURTYEIGHT", "THIRTYFIVE", "FOURTYONE", "THREE", "FIFTYTHREEE", "ONE", "FOURTYFIVE", "THIRTYEIGHT", "TWENTYEIGHT", "FIFTHYFIVE", "EIGHT", "TWENTYFIVE", "SIXTYONE", "TWENTY", "FOURTYSIX", "TWENTYONE", "TWENTYFOUR", "SIXTYTHREE", "FOURTY", "THIRTYFOUR", "SIXTY", "SEVENTEEN", "SIXTYFOUR", "THIRTYONE", "NINE", "TWENTYTWO", "FIFTY", "TWO", "ELEVEN", "THIRTEEN"]}, {"policy": "(((((\"TWENTYFOUR\" and \"FIFTHYFOUR\") and (\"FIFTEEN\" or \"THIRTYNINE\")) and (\"FOURTYONE\" or (\"FOURTYTHREE\" or (\"THIRTY\" or \"THIRTYSEVEN\")))) and (((\"FOURTY\" and \"THIRTYEIGHT\") or \"SIXTY\") or (\"THREE\" and (\"FIVE\" and \"SIX\")))) and (((\"FIFTHYEIGHT\" and (\"ELEVEN\" and (\"SEVEN\" or \"FOURTEEN\"))) or ((\"FIFTHYFIVE\" or \"SIXTYONE\") and (\"TWENTYFIVE\" and (\"SIXTEEN\" or (\"THIRTYONE\" or \"FIFTYTWO\"))))) or (((\"THIRTYFOUR\" and \"FIFTYTHREEE\") or (\"TWENTY\" or \"FOUR\")) and (\"THIRTYTHREE\" or ((\"SIXTYTWO\" or \"SIXTYTHREE\") and \"TWO\")))))", "key": ["TWENTYFOUR", "FIFTHYFOUR", "THIRTYNINE", "THIRTYSEVEN", "SIXTY", "TWENTY", "SIXTYTHREE", "TWO", "TWENTYNINE", "TWENTYONE", "THIRTYTWO", "FIFTYTWO", "EIGHT", "THIRTYONE", "FOURTYFIVE", "ELEVEN", "FIFTYONE", "FIFTHYSEVEN", "THIRTY", "FOURTYSEVEN", "FIVE", "FOUR", "TWELVE", "SIXTYONE", "FOURTYEIGHT", "THIRTYFIVE", "SIXTYTWO", "FIFTY", "SEVEN", "FOURTYTWO", "FOURTYNINE", "THREE"]}, {"policy": "(((((\"THIRTYNINE\" or \"THIRTYTHREE\") and (\"FOURTYONE\" or \"FOURTY\")) and (\"FIFTHYFOUR\" and (\"THIRTEEN\" and \"SIX\"))) or (((\"FIFTYTHREEE\" or \"FOURTYSIX\") or (\"FIFTHYSEVEN\" and \"FOURTYFIVE\")) and (\"TWENTY\" or (\"SIXTEEN\" or \"THIRTYSIX\")))) or (((((\"FIFTHYFIVE\" or \"TWENTYEIGHT\") and (\"THIRTYONE\" or \"SIXTYONE\")) and (\"FIFTEEN\" or (\"FIFTYONE\" and \"THIRTYFIVE\"))) or ((\"THIRTYSEVEN\" and \"SIXTY\") or (\"ONE\" and \"SIXTYTHREE\"))) and ((\"FIFTYTWO\" or (\"EIGHTEEN\" and \"FOURTYSEVEN\")) and (\"TWENTYNINE\" or ((\"FOURTYNINE\" and \"NINETEEN\") and \"THIRTYTWO\")))))", "key": ["FIFTHYFIVE", "SIXTYONE", "FIFTEEN", "EIGHTEEN", "FOURTYSEVEN", "FOURTYNINE", "NINETEEN", "THIRTYTWO", "FIFTYTWO", "THIRTYEIGHT", "TWENTYFOUR", "NINE", "TWENTYTWO", "TWENTYTHREE", "TWO", "TWENTY", "ELEVEN", "SEVENTEEN", "FIFTYONE", "FIFTHYFOUR", "THIRTYFIVE", "SIXTEEN", "THIRTY", "THIRTYNINE", "TWENTYFIVE", "FIFTHYNINE", "FOURTYFOUR", "TWELVE", "SIXTY", "FIFTHYEIGHT", "TWENTYSEVEN", "TWENTYNINE"]}, {"policy": "((((\"FOURTY\" or \"FIFTY\") or \"FOUR\") and (((\"FIFTHYFOUR\" and \"FOURTYSEVEN\") or (\"SEVEN\" and \"EIGHTEEN\")) or (\"ONE\" and \"SIXTY\"))) and (((((\"THIRTYNINE\" and (\"TEN\" or \"FOURTYFOUR\")) or (((\"THIRTYFIVE\" or \"TWENTYEIGHT\") or \"TWENTYNINE\") and (\"NINETEEN\" or \"FOURTYONE\"))) or (\"TWENTYFIVE\" and \"THIRTYONE\")) and (\"SIX\" or (\"FOURTYFIVE\" and \"FOURTYSIX\"))) or (((\"THIRTYTHREE\" or \"FIFTYTHREEE\") or (\"FIFTEEN\" or (\"THIRTYTWO\" and \"EIGHT\"))) or (\"FIVE\" or (((\"TWENTYONE\" or \"FIFTYONE\") and \"TWENTYTWO\") and \"THIRTYSEVEN\")))))", "key": ["FOUR", "ONE", "SIXTY", "TWENTYNINE", "NINETEEN", "FOURTYFIVE", "FOURTYSIX", "FIFTEEN", "FIFTHYSIX", "TWENTYTWO", "FOURTYNINE", "SIX", "SEVENTEEN", "THREE", "FIVE", "FIFTHYEIGHT", "THIRTYEIGHT", "EIGHT", "THIRTYFOUR", "TWENTYSIX", "SEVEN", "FOURTYSEVEN", "TWO", "FIFTHYFOUR", "FIFTYTWO", "THIRTYONE", "THIRTYTHREE", "EIGHTEEN", "THIRTYTWO", "FOURTYTWO", "TWENTYSEVEN", "TWENTYFIVE"]}, {"policy": "((((\"FOURTYSIX\" and \"FOURTYEIGHT\") or ((\"FIFTEEN\" and \"ELEVEN\") or ((\"TWELVE\" or \"SEVEN\") and (\"FIFTHYFIVE\" or (\"THIRTYTWO\" and \"FOURTEEN\"))))) and ((\"FIFTY\" or ((\"TEN\" or \"FOURTYFOUR\") or ((\"EIGHT\" or \"THIRTEEN\") or \"FIFTYTHREEE\"))) or (\"TWENTYFOUR\" and (\"FOURTYONE\" and (\"TWENTYTHREE\" and \"THIRTYTHREE\"))))) and (((((\"THIRTYFOUR\" or \"TWO\") and (\"FIFTHYSEVEN\" or (\"FOURTY\" and \"TWENTY\"))) or \"FOURTYNINE\") and ((\"NINETEEN\" or \"SIXTYONE\") and (\"THIRTYSEVEN\" and \"THIRTYFIVE\"))) and (\"SEVENTEEN\" and (\"TWENTYTWO\" or \"FIFTHYEIGHT\"))))", "key": ["FOURTYSIX", "FOURTYEIGHT", "FIFTYTHREEE", "TWO", "FOURTY", "TWENTY", "NINETEEN", "THIRTYSEVEN", "THIRTYFIVE", "SEVENTEEN", "TWENTYTWO", "NINE", "TEN", "FOUR", "FOURTYONE", "FOURTYFOUR", "FOURTYSEVEN", "FIFTY", "TWENTYFOUR", "FIFTYONE", "SEVEN", "ONE", "FIFTHYSEVEN", "FOURTYNINE", "FIFTHYSIX", "SIXTYONE", "SIX", "THREE", "THIRTYSIX", "TWENTYEIGHT", "TWELVE", "THIRTYTWO"]}, {"policy": "((((\"EIGHTEEN\" or ((\"THIRTYTWO\" or \"FIFTEEN\") and \"THIRTYFOUR\")) or (\"NINETEEN\" and \"FOURTYSIX\")) and (((\"FOURTYFIVE\" and \"FOURTEEN\") and (\"THIRTEEN\" and \"FOURTYFOUR\")) or (\"THIRTYNINE\" and (\"TWENTYONE\" and \"THREE\")))) or (((\"FIFTHYSIX\" or ((\"FIFTY\" or \"FIFTHYFIVE\") or \"SIXTYTWO\")) or ((\"FOURTYEIGHT\" and (\"FIFTHYSEVEN\" or \"FIFTYONE\")) and (\"SEVEN\" or \"TWENTYNINE\"))) or ((((\"SIXTYONE\" or \"SIXTY\") or ((\"TEN\" or \"THIRTYONE\") and \"THIRTYSIX\")) and ((\"TWO\" and \"SIXTYFOUR\") and \"SIXTEEN\")) or (\"EIGHT\" and \"FIVE\"))))", "key": ["NINETEEN", "FOURTYSIX", "THIRTYNINE", "TWENTYONE", "THREE", "FIFTEEN", "FIFTHYSEVEN", "THIRTYFIVE", "FOURTY", "FIFTYTHREEE", "SIXTY", "FOURTYEIGHT", "EIGHT", "SEVEN", "FOURTEEN", "THIRTYFOUR", "FIFTHYEIGHT", "THIRTYTHREE", "FOURTYNINE", "THIRTYSEVEN", "TWENTYTWO", "TWENTYSEVEN", "FOURTYONE", "SIXTYTWO", "TWENTYTHREE", "TWENTYSIX", "FOURTYSEVEN", "FIVE", "ELEVEN", "THIRTYEIGHT", "THIRTYTWO", "SIXTYONE"]}]